invenio_catalogue_marc21/__init__.py
invenio_catalogue_marc21/cli.py
invenio_catalogue_marc21/config.py
invenio_catalogue_marc21/ext.py
invenio_catalogue_marc21/proxies.py
invenio_catalogue_marc21/utils.py
invenio_catalogue_marc21/views.py
invenio_catalogue_marc21/fixtures/__init__.py
invenio_catalogue_marc21/fixtures/demo.py
invenio_catalogue_marc21/fixtures/tasks.py
invenio_catalogue_marc21/records/__init__.py
invenio_catalogue_marc21/records/api.py
invenio_catalogue_marc21/records/jsonschemas/__init__.py
invenio_catalogue_marc21/records/jsonschemas/marc21-catalogue/marc21-catalogue-v1.0.0.json
invenio_catalogue_marc21/records/systemfields/__init__.py
invenio_catalogue_marc21/records/systemfields/catalogue_check.py
invenio_catalogue_marc21/resources/__init__.py
invenio_catalogue_marc21/resources/args.py
invenio_catalogue_marc21/resources/config.py
invenio_catalogue_marc21/resources/resources.py
invenio_catalogue_marc21/resources/deserializers/__init__.py
invenio_catalogue_marc21/resources/deserializers/deserializer.py
invenio_catalogue_marc21/resources/deserializers/schema.py
invenio_catalogue_marc21/resources/serializers/__init__.py
invenio_catalogue_marc21/resources/serializers/base/__init__.py
invenio_catalogue_marc21/resources/serializers/base/schema.py
invenio_catalogue_marc21/resources/serializers/base/serializer.py
invenio_catalogue_marc21/resources/serializers/catalogue/__init__.py
invenio_catalogue_marc21/resources/serializers/catalogue/schema.py
invenio_catalogue_marc21/resources/serializers/catalogue/serializer.py
invenio_catalogue_marc21/resources/serializers/deposit/__init__.py
invenio_catalogue_marc21/resources/serializers/deposit/schema.py
invenio_catalogue_marc21/resources/serializers/deposit/serializer.py
invenio_catalogue_marc21/resources/serializers/fields/__init__.py
invenio_catalogue_marc21/resources/serializers/fields/metadata.py
invenio_catalogue_marc21/resources/serializers/ui/__init__.py
invenio_catalogue_marc21-0.0.4.dist-info/METADATA
invenio_catalogue_marc21-0.0.4.dist-info/WHEEL
invenio_catalogue_marc21-0.0.4.dist-info/entry_points.txt
invenio_catalogue_marc21-0.0.4.dist-info/licenses/AUTHORS.rst
invenio_catalogue_marc21-0.0.4.dist-info/licenses/LICENSE
invenio_catalogue_marc21-0.0.4.dist-info/RECORD
