Metadata-Version: 2.4
Name: invenio-catalogue-marc21
Version: 0.0.4
Summary: Invenio module link multiple marc21 records modules.
Project-URL: Repository, https://github.com/tu-graz-library/invenio-catalogue-marc21
Author-email: Graz University of Technology <info@tugraz.at>
License: MIT License
License-File: AUTHORS.rst
License-File: LICENSE
Keywords: catalogue,invenio,publications,tugraz
Classifier: Development Status :: 4 - Beta
Classifier: License :: OSI Approved :: MIT License
Classifier: Operating System :: OS Independent
Classifier: Programming Language :: Python
Classifier: Topic :: Software Development :: Libraries :: Python Modules
Requires-Python: >=3.12
Requires-Dist: faker-file[pdf]>0.17.0
Requires-Dist: faker>=9.0.0
Requires-Dist: invenio-base<3.0.0,>=2.0.0
Requires-Dist: invenio-i18n<4.0.0,>=3.0.0
Requires-Dist: invenio-records-marc21<1.0.0,>=0.20.0
Requires-Dist: invenio-search[opensearch2]<4.0.0,>=3.0.0
Requires-Dist: reportlab>=4.0.0
Provides-Extra: tests
Requires-Dist: invenio-app<3.0.0,>=2.0.0; extra == 'tests'
Requires-Dist: pytest-black>=0.6.0; extra == 'tests'
Requires-Dist: pytest-invenio<4.0.0,>=3.0.0; extra == 'tests'
Requires-Dist: ruff>=0.11; extra == 'tests'
Requires-Dist: sphinx>=8.0.0; extra == 'tests'
